fastdeploy/__init__.py
fastdeploy/__main__.py
fastdeploy/_infer.py
fastdeploy/_loop.py
fastdeploy/_rest.py
fastdeploy/_utils.py
fastdeploy-3.1.1.dist-info/LICENSE
fastdeploy-3.1.1.dist-info/METADATA
fastdeploy-3.1.1.dist-info/WHEEL
fastdeploy-3.1.1.dist-info/entry_points.txt
fastdeploy-3.1.1.dist-info/top_level.txt
fastdeploy-3.1.1.dist-info/RECORD
