Metadata-Version: 2.1
Name: fastdeploy
Version: 3.1.1
Summary: Deploy DL/ ML inference pipelines with minimal extra code. 
Home-page: https://github.com/notAI-tech/fastDeploy
Author: BEDAPUDI PRANEETH
Author-email: praneeth@bpraneeth.com
License: MIT
Classifier: License :: OSI Approved :: MIT License
Classifier: Programming Language :: Python
Classifier: Programming Language :: Python :: 3
Classifier: Programming Language :: Python :: 3.6
Classifier: Programming Language :: Python :: Implementation :: CPython
Requires-Python: >=3.6.0
License-File: LICENSE
Requires-Dist: falcon
Requires-Dist: liteindex ==0.0.3.2.dev6
Requires-Dist: zstandard
Requires-Dist: gunicorn[gevent]
Requires-Dist: msgpack
Requires-Dist: psutil
